LICENSE
partial/__init__.py
partial/partial.py
partial/placeholder.py
partial/py.typed
python_partial-0.0.6.dist-info/LICENSE
python_partial-0.0.6.dist-info/METADATA
python_partial-0.0.6.dist-info/WHEEL
python_partial-0.0.6.dist-info/RECORD
