Metadata-Version: 2.1
Name: python-partial
Version: 0.0.6
Summary: Python partial.
Home-page: https://github.com/ChenyangGao/web-mount-packs/tree/main/python-module/python-partial
License: MIT
Keywords: partial,currying,placeholder
Author: ChenyangGao
Author-email: wosiwujm@gmail.com
Requires-Python: >=3.11,<4.0
Classifier: Development Status :: 5 - Production/Stable
Classifier: Intended Audience :: Developers
Classifier: License :: OSI Approved :: MIT License
Classifier: Operating System :: OS Independent
Classifier: Programming Language :: Python
Classifier: Programming Language :: Python :: 3
Classifier: Programming Language :: Python :: 3.11
Classifier: Programming Language :: Python :: 3.12
Classifier: Programming Language :: Python :: 3 :: Only
Classifier: Topic :: Software Development
Classifier: Topic :: Software Development :: Libraries
Classifier: Topic :: Software Development :: Libraries :: Python Modules
Requires-Dist: python-undefined (>=0.0.3)
Project-URL: Repository, https://github.com/ChenyangGao/web-mount-packs/tree/main/python-module/python-partial
